{
    "mobileBottomRow": 10,
    "widgetName": "Text6",
    "dynamicPropertyPathList": [{"key": "isVisible"}],
    "displayName": "Text",
    "iconSVG": "/static/media/icon.a47d6d5dbbb718c4dc4b2eb4f218c1b7.svg",
    "searchTags": [
        "typography",
        "paragraph",
        "label"
    ],
    "topRow": 6,
    "bottomRow": 10,
    "parentRowSpace": 10,
    "type": "TEXT_WIDGET",
    "hideCard": false,
    "mobileRightColumn": 16,
    "animateLoading": true,
    "overflow": "NONE",
    "fontFamily": "System Default",
    "parentColumnSpace": 16.4375,
    "dynamicTriggerPathList": [],
    "leftColumn": 3,
    "dynamicBindingPathList": [
        {"key": "truncateButtonColor"},
        {"key": "borderRadius"},
        {"key": "isVisible"}
    ],
    "shouldTruncate": false,
    "truncateButtonColor": "{{appsmith.theme.colors.primaryColor}}",
    "text": "Nothing here yet! Create a new plan to start!",
    "key": "jo6zbp8gtd",
    "isDeprecated": false,
    "rightColumn": 62,
    "textAlign": "CENTER",
    "dynamicHeight": "AUTO_HEIGHT",
    "widgetId": "jmw4j9bzzn",
    "minWidth": 450,
    "isVisible": "{{GetClientWorkoutPlan.data.length == 0}}",
    "fontStyle": "BOLD",
    "textColor": "#231F20",
    "version": 1,
    "parentId": "0hr9zsv61u",
    "tags": [
        "Suggested",
        "Content"
    ],
    "renderMode": "CANVAS",
    "isLoading": false,
    "mobileTopRow": 6,
    "responsiveBehavior": "fill",
    "originalTopRow": 4,
    "borderRadius": "{{appsmith.theme.borderRadius.appBorderRadius}}",
    "mobileLeftColumn": 0,
    "maxDynamicHeight": 9000,
    "originalBottomRow": 9,
    "fontSize": "1.25rem",
    "minDynamicHeight": 4
}